prf_api/__init__.py
prf_api/acidentes.py
prf_api/arquivo.py
prf_api/cli.py
prf_api/infracoes.py
prf_api/prf_api.py
prf_api-0.2.2.dist-info/AUTHORS.rst
prf_api-0.2.2.dist-info/LICENSE
prf_api-0.2.2.dist-info/METADATA
prf_api-0.2.2.dist-info/WHEEL
prf_api-0.2.2.dist-info/entry_points.txt
prf_api-0.2.2.dist-info/top_level.txt
prf_api-0.2.2.dist-info/RECORD
