Metadata-Version: 2.1
Name: prf-api
Version: 0.2.2
Summary: API de dados abertos da PRF
Home-page: https://github.com/nymarya/prf_api
Author: Mayra Azevedo
Author-email: mayradazevedo@ufrn.edu.br
License: MIT license
Keywords: prf,wrapper
Platform: UNKNOWN
Classifier: Development Status :: 2 - Pre-Alpha
Classifier: Intended Audience :: Developers
Classifier: License :: OSI Approved :: MIT License
Classifier: Natural Language :: Portuguese
Classifier: Programming Language :: Python :: 2
Classifier: Programming Language :: Python :: 2.7
Classifier: Programming Language :: Python :: 3
Classifier: Programming Language :: Python :: 3.4
Classifier: Programming Language :: Python :: 3.5
Classifier: Programming Language :: Python :: 3.6
Classifier: Programming Language :: Python :: 3.7
Requires-Dist: Click (>=6.0)
Requires-Dist: requests (==2.22.0)
Requires-Dist: pandas (==0.24.2)
Requires-Dist: rarfile (==3.0)
Requires-Dist: beautifulsoup4 (==4.7.1)
Requires-Dist: unrar (==0.3)
